perigramma/__init__.py
perigramma/cli.py
perigramma/properties.py
perigramma/registry.py
perigramma/scaffold.py
perigramma/template_classes/__init__.py
perigramma/template_classes/_none.py
perigramma/template_classes/base.py
perigramma/template_classes/dict_template.py
perigramma/template_classes/filesystem_template.py
perigramma/template_classes/git_template.py
perigramma/template_lib/setuptools_pyproject/template/src/{{ project_name }}/__init__.py
perigramma/template_lib/setuptools_pyproject/template/src/{{ project_name }}/main.py
perigramma/templaters/__init__.py
perigramma/templaters/base.py
perigramma/templaters/jinja.py
perigramma/templaters/pystring.py
perigramma/templaters/registry.py
perigramma-0.1.1.dist-info/METADATA
perigramma-0.1.1.dist-info/WHEEL
perigramma-0.1.1.dist-info/entry_points.txt
perigramma-0.1.1.dist-info/top_level.txt
perigramma-0.1.1.dist-info/RECORD
