Metadata-Version: 2.4
Name: perigramma
Version: 0.1.1
Summary: A tool to scaffold a projects from templates
Author-email: John Raines <johndanielraines@gmail.com>
Classifier: Programming Language :: Python :: 3
Requires-Python: >=3.10
Requires-Dist: pyyaml>=6.0
Requires-Dist: Jinja2==3.1.6
Requires-Dist: GitPython==3.1.44
Provides-Extra: dev
Requires-Dist: pytest; extra == "dev"
Requires-Dist: pytest-cov; extra == "dev"
